{"GlobalPropertiesHash":"SC2TVsh1zXklEa7ngIFTPFLFcBfTvHasvXf5gMngSQk=","FingerprintPatternsHash":"gq3WsqcKBUGTSNle7RKKyXRIwh7M8ccEqOqYvIzoM04=","PropertyOverridesHash":"8ZRc1sGeVrPBx4lD717BgRaQekyh78QKV9SKsdt638U=","InputHashes":["reCzd23kmhpvXnwkcCIMEF2FOm8zH8yUA8y7H/cZba0=","CXwM33NF7P0c7xRBbfzYD30cdSoj3ptfxK54zntWxzU=","RaVuvTAE2up4bOeJu9DNBKEkusixTTDqAAPysarphuA=","Ns49c0hJyOi6Z9nVgUl2zF1e4k5LeahTHlhrngnJ4es=","2ujJJ57aEjuZs3dqvlDU4\u002BhHxqSAopFh7OMbarRTrNw=","WOKaF7gnnGPjS5zTGEjvWXOvDq0EVHbdgQsr6DHNm14=","BRpAunkbUsWeQmj8v1jhHsbVcTbHJFEKohAT\u002BjXGR3o=","DIj/yWQDOp0UcqwTiqFHVVCg2XLtbkYyj\u002BAds4x8MTY=","82CG//I6OnmXmuVgc7jscpbwjW2CZb8O88zB1/moatQ=","wCSzRu19q0E0NUfwDMelAclghOyLRQ4BKp\u002BIzP5B36I=","JfhKb2jRQ44LtT7rKRH2QWw2TfVvHqYtXJDehJRWGO4=","g795v7/OUR1RF3ngK4GXlHWzNPQWw5\u002B4aGpFx\u002BJ/Vjs=","VVoi6BN/7ODN0CObML8GmXNhCm5p5hmhJpkeJnbbDF0=","\u002BALpAZNVkvDRpMMPHJszJJPQrJ2GzxXAGQ1SjjA/UaQ=","zZZxBOpGcQ7RjyzZPCTN4tdYjxxxstPMjwp/zCoKKCM=","/MQ6CitdL\u002B\u002BX\u002Bs3YScvvSH/EY/I9e5szTsJE/6VgDIY=","Jq0rMTtDpCdUGzpQoM3PxzPuQEAazQOQw4grSqv\u002Bm0c=","PHsuJyGAC6u6EPS5OVI1fYE8SCjxOf4YZTJzB6wTejQ=","XxkvTdYfV3NiJZZIOD3vxjGG7n9Z0DuLb\u002BOzCqQ0laM=","CVIsmYz3skYrTha1fUT8MXrPEYgwPVpBrrrKpqpAACU=","XAw54n5hfMyxiWVAG4qXzDjwi91aZv23HWgrlPFI7\u002BA=","iIcBHEEEambAAXjjmQXYV3RHdu1LdcadUIEEcZqiauc="],"CachedAssets":{"reCzd23kmhpvXnwkcCIMEF2FOm8zH8yUA8y7H/cZba0=":{"Identity":"C:\\Users\\bruger\\Desktop\\Opgaver\\Pr10\\RecipeManager\\wwwroot\\app.css","SourceId":"RecipeManager","SourceType":"Discovered","ContentRoot":"C:\\Users\\bruger\\Desktop\\Opgaver\\Pr10\\RecipeManager\\wwwroot\\","BasePath":"/","RelativePath":"app#[.{fingerprint}]?.css","AssetKind":"All","AssetMode":"All","AssetRole":"Primary","AssetMergeBehavior":null,"AssetMergeSource":"","RelatedAsset":null,"AssetTraitName":null,"AssetTraitValue":null,"Fingerprint":"da95v2qkru","Integrity":"u9qEka1auR7E3rd3/8/j8hkQdSOYj9bRJ4nYiFDR1sE=","CopyToOutputDirectory":"Never","CopyToPublishDirectory":"PreserveNewest","OriginalItemSpec":"wwwroot\\app.css","FileLength":2591,"LastWriteTime":"2025-11-12T09:06:08.7093467+00:00"},"CXwM33NF7P0c7xRBbfzYD30cdSoj3ptfxK54zntWxzU=":{"Identity":"C:\\Users\\bruger\\Desktop\\Opgaver\\Pr10\\RecipeManager\\wwwroot\\bootstrap\\bootstrap.min.css","SourceId":"RecipeManager","SourceType":"Discovered","ContentRoot":"C:\\Users\\bruger\\Desktop\\Opgaver\\Pr10\\RecipeManager\\wwwroot\\","BasePath":"/","RelativePath":"bootstrap/bootstrap.min#[.{fingerprint}]?.css","AssetKind":"All","AssetMode":"All","AssetRole":"Primary","AssetMergeBehavior":null,"AssetMergeSource":"","RelatedAsset":null,"AssetTraitName":null,"AssetTraitValue":null,"Fingerprint":"bpk8xqwxhs","Integrity":"z8OR40MowJ8GgK6P89Y\u002BhiJK5\u002BcclzFHzLhFQLL92bg=","CopyToOutputDirectory":"Never","CopyToPublishDirectory":"PreserveNewest","OriginalItemSpec":"wwwroot\\bootstrap\\bootstrap.min.css","FileLength":162720,"LastWriteTime":"2025-11-12T09:06:08.8373829+00:00"},"RaVuvTAE2up4bOeJu9DNBKEkusixTTDqAAPysarphuA=":{"Identity":"C:\\Users\\bruger\\Desktop\\Opgaver\\Pr10\\RecipeManager\\wwwroot\\bootstrap\\bootstrap.min.css.map","SourceId":"RecipeManager","SourceType":"Discovered","ContentRoot":"C:\\Users\\bruger\\Desktop\\Opgaver\\Pr10\\RecipeManager\\wwwroot\\","BasePath":"/","RelativePath":"bootstrap/bootstrap.min.css#[.{fingerprint}]?.map","AssetKind":"All","AssetMode":"All","AssetRole":"Primary","AssetMergeBehavior":null,"AssetMergeSource":"","RelatedAsset":null,"AssetTraitName":null,"AssetTraitValue":null,"Fingerprint":"8inm30yfxf","Integrity":"gBwg2tmA0Ci2u54gMF1jNCVku6vznarkLS6D76htNNQ=","CopyToOutputDirectory":"Never","CopyToPublishDirectory":"PreserveNewest","OriginalItemSpec":"wwwroot\\bootstrap\\bootstrap.min.css.map","FileLength":449111,"LastWriteTime":"2025-11-12T09:06:08.840372+00:00"},"Ns49c0hJyOi6Z9nVgUl2zF1e4k5LeahTHlhrngnJ4es=":{"Identity":"C:\\Users\\bruger\\Desktop\\Opgaver\\Pr10\\RecipeManager\\wwwroot\\favicon.png","SourceId":"RecipeManager","SourceType":"Discovered","ContentRoot":"C:\\Users\\bruger\\Desktop\\Opgaver\\Pr10\\RecipeManager\\wwwroot\\","BasePath":"/","RelativePath":"favicon#[.{fingerprint}]?.png","AssetKind":"All","AssetMode":"All","AssetRole":"Primary","AssetMergeBehavior":null,"AssetMergeSource":"","RelatedAsset":null,"AssetTraitName":null,"AssetTraitValue":null,"Fingerprint":"ifv42okdf2","Integrity":"4mWsDy3aHl36ZbGt8zByK7Pvd4kRUoNgTYzRnwmPHwg=","CopyToOutputDirectory":"Never","CopyToPublishDirectory":"PreserveNewest","OriginalItemSpec":"wwwroot\\favicon.png","FileLength":1148,"LastWriteTime":"2025-11-12T09:06:08.7113468+00:00"}},"CachedCopyCandidates":{}}